inkjet/__init__.py
inkjet/__main__.py
inkjet/cli.py
inkjet/config.py
inkjet/discovery.py
inkjet/image.py
inkjet/output.py
inkjet/printer.py
inkjet/text.py
inkjet-0.1.0.dist-info/METADATA
inkjet-0.1.0.dist-info/WHEEL
inkjet-0.1.0.dist-info/entry_points.txt
inkjet-0.1.0.dist-info/licenses/LICENSE
inkjet-0.1.0.dist-info/RECORD
