Metadata-Version: 2.4
Name: inkjet
Version: 0.1.0
Summary: CLI tool for Bluetooth thermal printer control and printing
Project-URL: Homepage, https://github.com/AaronChartier/inkjet
Project-URL: Repository, https://github.com/AaronChartier/inkjet
Project-URL: Documentation, https://github.com/AaronChartier/inkjet#readme
Author: Aaron Chartier
License-Expression: MIT
License-File: LICENSE
Keywords: ble,bluetooth,cli,printer,receipt,thermal
Classifier: Development Status :: 3 - Alpha
Classifier: Environment :: Console
Classifier: Intended Audience :: Developers
Classifier: License :: OSI Approved :: MIT License
Classifier: Operating System :: MacOS
Classifier: Operating System :: POSIX :: Linux
Classifier: Programming Language :: Python :: 3
Classifier: Programming Language :: Python :: 3.10
Classifier: Programming Language :: Python :: 3.11
Classifier: Programming Language :: Python :: 3.12
Classifier: Topic :: Printing
Classifier: Topic :: Utilities
Requires-Python: >=3.9
Requires-Dist: bleak>=0.21.0
Requires-Dist: pillow>=9.0.0
Requires-Dist: python-barcode>=0.15.0
Requires-Dist: qrcode[pil]>=7.0
Requires-Dist: rich>=13.0.0
Requires-Dist: typer[all]>=0.9.0
Provides-Extra: dev
Requires-Dist: pytest-asyncio>=0.21.0; extra == 'dev'
Requires-Dist: pytest>=7.0.0; extra == 'dev'
Requires-Dist: ruff>=0.1.0; extra == 'dev'
